{"ZAF": ["M 191 200 Q 486.6 237.0 676 468", "South Africa", "365"], "ZWE": ["M 191 200 Q 488.6 209.8 697 423", "Zimbabwe", "248"], "BRA": ["M 191 200 Q 349.0 255.0 426 405", "Brazil", "168"], "USA": ["M 191 200 Q 236.0 184.2 280 205", "United States of America", "139"], "JAM": ["M 191 200 Q 281.8 208.8 342 279", "Jamaica", "84"], "DOM": ["M 191 200 Q 293.4 203.0 366 277", "Dominican Republic", "82"], "MWI": ["M 191 200 Q 492.2 195.4 714 401", "Malawi", "63"], "CAN": ["M 191 200 Q 204.2 154.2 245 131", "Canada", "35"], "CHL": ["M 191 200 Q 333.6 310.0 361 488", "Chile", "33"], "MTQ": ["M 191 200 Q 311.6 205.0 396 293", "Martinique", "23"]}