{"USA": ["M 641 179 Q 454.8 119.8 280 205", "United States of America", "3730"], "FRA": ["M 641 179 Q 625.8 167.2 607 170", "France", "1066"], "CHL": ["M 641 179 Q 439.2 277.0 361 488", "Chile", "799"], "BEL": ["M 641 179 Q 632.2 160.6 614 153", "Belgium", "799"], "GBR": ["M 641 179 Q 623.0 145.4 588 134", "United Kingdom", "533"], "GRC": ["M 641 179 Q 659.8 181.8 672 198", "Greece", "533"], "IRN": ["M 641 179 Q 702.2 166.0 756 200", "Iran, Islamic Rep.", "533"], "SCG": ["M 641 179 Q 495.2 117.2 347 173", "Serbia and Montenegro", "274"], "SWE": ["M 641 179 Q 638.4 142.8 662 116", "Sweden", "266"], "IRL": ["M 641 179 Q 613.4 146.2 572 142", "Ireland", "133"]}