{"USA": ["M 395 290 Q 354.0 224.0 280 205", "United States of America", "17967"], "GLP": ["M 395 290 Q 394.8 287.8 394 286", "Guadeloupe", "6275"], "VIR": ["M 395 290 Q 468.8 178.2 599 149", "Virgin Islands, British ", "4919"], "PRI": ["M 395 290 Q 388.2 280.6 378 279", "Puerto Rico", "2919"], "CAN": ["M 395 290 Q 351.8 180.0 245 131", "Canada", "2745"], "ATG": ["M 395 290 Q 395.4 285.8 394 283", "Antigua and Barbuda", "2675"], "VGB": ["M 395 290 Q 391.4 281.6 383 278", "Virgin Islands, U.S.", "656"], "BRB": ["M 395 290 Q 399.6 292.8 401 298", "Barbados", "540"], "ESP": ["M 395 290 Q 471.4 202.6 587 192", "Spain", "357"], "JAM": ["M 395 290 Q 370.2 273.4 342 279", "Jamaica", "308"]}