{"USA": ["M 599 149 Q 427.8 113.2 280 205", "United States of America", "15745"], "DMA": ["M 599 149 Q 468.8 178.2 395 290", "Dominica", "4919"], "ATG": ["M 599 149 Q 469.2 175.0 394 283", "Antigua and Barbuda", "4842"], "PRI": ["M 599 149 Q 462.0 169.8 378 279", "Puerto Rico", "4345"], "DOM": ["M 599 149 Q 456.4 166.4 366 277", "Dominican Republic", "3201"], "VGB": ["M 599 149 Q 465.2 169.8 383 278", "Virgin Islands, U.S.", "2733"], "TTO": ["M 599 149 Q 465.2 187.2 395 308", "Trinidad and Tobago", "2134"], "AIA": ["M 599 149 Q 468.0 172.0 389 279", "Anguilla", "1105"], "GRD": ["M 599 149 Q 465.4 184.0 394 302", "Grenada", "882"], "CUB": ["M 599 149 Q 445.6 155.2 340 266", "Cuba", "650"]}